haze/__init__.py
haze/auth.py
haze/config.py
haze/exceptions.py
haze/id.py
haze/jwt.py
haze/serializers.py
haze/storage.py
haze/utils.py
haze_auth-0.1.2.dist-info/METADATA
haze_auth-0.1.2.dist-info/WHEEL
haze_auth-0.1.2.dist-info/licenses/LICENSE.md
haze_auth-0.1.2.dist-info/RECORD
