Metadata-Version: 2.4
Name: haze-auth
Version: 0.1.2
Summary: Lightning-Fast Magic Link Authentication
Project-URL: Homepage, https://github.com/itsmeadarsh2008/haze
Project-URL: Repository, https://github.com/itsmeadarsh2008/haze
Project-URL: Issues, https://github.com/itsmeadarsh2008/haze/issues
Project-URL: Documentation, https://github.com/itsmeadarsh2008/haze/blob/main/README.md
Author-email: Adarsh Gourab Mahalik <adarshgourabmahalik@outlook.com>
License: ## Haze License v1.0
License-File: LICENSE.md
Keywords: authentication,jwt,magic-link,security,web
Classifier: Development Status :: 4 - Beta
Classifier: Intended Audience :: Developers
Classifier: License :: OSI Approved :: MIT License
Classifier: Operating System :: OS Independent
Classifier: Programming Language :: Python :: 3
Classifier: Programming Language :: Python :: 3.8
Classifier: Programming Language :: Python :: 3.9
Classifier: Programming Language :: Python :: 3.10
Classifier: Programming Language :: Python :: 3.11
Classifier: Programming Language :: Python :: 3.12
Classifier: Topic :: Security :: Cryptography
Classifier: Topic :: Software Development :: Libraries :: Python Modules
Requires-Python: >=3.8
Requires-Dist: cryptography>=3.4.0
Provides-Extra: full
Requires-Dist: msgpack>=1.0.3; extra == 'full'
Requires-Dist: nanoid>=2.0.0; extra == 'full'
Requires-Dist: orjson>=3.6.0; extra == 'full'
Requires-Dist: pyjwt>=2.3.0; extra == 'full'
Provides-Extra: json
Requires-Dist: orjson>=3.6.0; extra == 'json'
Provides-Extra: jwt
Requires-Dist: pyjwt>=2.3.0; extra == 'jwt'
Provides-Extra: msgpack
Requires-Dist: msgpack>=1.0.3; extra == 'msgpack'
Provides-Extra: nanoid
Requires-Dist: nanoid>=2.0.0; extra == 'nanoid'
